_rqtreemesh.cp310-win32.pyd
rqtreemesh/__init__.py
rqtreemesh-1.0.1.dist-info/LICENSE.txt
rqtreemesh-1.0.1.dist-info/METADATA
rqtreemesh-1.0.1.dist-info/WHEEL
rqtreemesh-1.0.1.dist-info/top_level.txt
rqtreemesh-1.0.1.dist-info/RECORD
