Metadata-Version: 2.1
Name: rqtreemesh
Version: 1.0.1
Summary: An implementation of restricted quadtree triangulation (RQT), for converting raster heightmaps to 3D meshes.
Home-page: https://github.com/philipschall/rqtreemesh
Author: Philip Schall
Author-email: philip.schall@live.com
License: Unlicense
Classifier: Development Status :: 3 - Alpha
Classifier: Intended Audience :: Developers
Classifier: License :: Public Domain
Classifier: Operating System :: Microsoft :: Windows
Classifier: Operating System :: Unix
Classifier: Operating System :: MacOS
Classifier: Programming Language :: C++
Classifier: Programming Language :: Python
Classifier: Programming Language :: Python :: 3
Classifier: Programming Language :: Python :: 3.9
Classifier: Programming Language :: Python :: 3.10
Classifier: Programming Language :: Python :: 3.11
Classifier: Programming Language :: Python :: 3 :: Only
Requires-Python: >=3.9
License-File: LICENSE.txt
Requires-Dist: numpy
Requires-Dist: pillow
